LICENSE
MANIFEST.in
README.rst
setup.py
./autodoc/__init__.py
./autodoc/_compat.py
autodoc/__init__.py
autodoc/_compat.py
autodoc.egg-info/PKG-INFO
autodoc.egg-info/SOURCES.txt
autodoc.egg-info/dependency_links.txt
autodoc.egg-info/requires.txt
autodoc.egg-info/top_level.txt
autodoc/templates/template.md
autodoc/templates/template.rst
docs/Makefile
docs/make.bat
docs/source/conf.py
docs/source/index.rst